[{"page":1,"angle":0,"width":1449,"height":750,"unit":"pixel","lines":[{"boundingBox":[38,28,343,28,343,61,38,60],"appearance":{"style":{"name":"other","confidence":0.972}},"text":"GMK Earth Tones","words":[{"boundingBox":[39,29,115,30,114,60,38,60],"text":"GMK","confidence":0.998},{"boundingBox":[132,30,220,30,220,61,131,61],"text":"Earth","confidence":0.998},{"boundingBox":[235,30,338,29,339,62,235,61],"text":"Tones","confidence":0.998}]},{"boundingBox":[592,32,808,32,808,66,592,66],"appearance":{"style":{"name":"other","confidence":0.972}},"text":"Final with extras","words":[{"boundingBox":[594,33,653,34,652,67,592,66],"text":"Final","confidence":0.993},{"boundingBox":[660,34,716,35,715,67,659,67],"text":"with","confidence":0.989},{"boundingBox":[722,35,809,33,809,67,722,67],"text":"extras","confidence":0.997}]},{"boundingBox":[1023,36,1419,35,1419,67,1023,68],"appearance":{"style":{"name":"other","confidence":0.972}},"text":"ran 19 July thru 19 Aug 2021","words":[{"boundingBox":[1025,38,1065,38,1064,68,1024,68],"text":"ran","confidence":0.994},{"boundingBox":[1076,37,1107,37,1106,68,1075,68],"text":"19","confidence":0.998},{"boundingBox":[1113,37,1171,37,1170,69,1112,68],"text":"July","confidence":0.988},{"boundingBox":[1177,37,1234,37,1234,69,1177,69],"text":"thru","confidence":0.991},{"boundingBox":[1243,37,1277,37,1278,68,1243,69],"text":"19","confidence":0.998},{"boundingBox":[1284,37,1341,36,1342,68,1284,68],"text":"Aug","confidence":0.998},{"boundingBox":[1348,36,1418,35,1419,67,1349,68],"text":"2021","confidence":0.991}]},{"boundingBox":[27,107,62,106,62,126,27,125],"appearance":{"style":{"name":"other","confidence":0.972}},"text":"Base","words":[{"boundingBox":[27,106,62,106,62,126,27,126],"text":"Base","confidence":0.989}]},{"boundingBox":[72,96,310,95,310,123,72,124],"appearance":{"style":{"name":"other","confidence":0.972}},"text":"Earth Tones - $125","words":[{"boundingBox":[72,98,136,97,136,124,73,124],"text":"Earth","confidence":0.994},{"boundingBox":[144,97,217,97,218,124,144,124],"text":"Tones","confidence":0.997},{"boundingBox":[223,97,238,96,239,124,223,124],"text":"-","confidence":0.994},{"boundingBox":[244,96,308,96,309,124,245,124],"text":"$125","confidence":0.991}]},{"boundingBox":[350,100,478,99,478,122,350,122],"appearance":{"style":{"name":"other","confidence":0.972}},"text":"1500/500","words":[{"boundingBox":[350,100,471,100,471,122,351,123],"text":"1500/500","confidence":0.955}]},{"boundingBox":[25,163,100,164,100,188,25,186],"appearance":{"style":{"name":"other","confidence":0.945}},"text":"Alt Alphas","words":[{"boundingBox":[27,163,42,164,41,187,25,187],"text":"Alt","confidence":0.994},{"boundingBox":[47,164,100,164,99,189,45,187],"text":"Alphas","confidence":0.997}]},{"boundingBox":[131,156,310,156,310,184,131,185],"appearance":{"style":{"name":"other","confidence":0.972}},"text":"Oxidane- $60","words":[{"boundingBox":[131,156,254,157,254,185,131,186],"text":"Oxidane-","confidence":0.969},{"boundingBox":[260,157,307,156,307,185,260,185],"text":"$60","confidence":0.987}]},{"boundingBox":[348,160,462,159,462,183,348,184],"appearance":{"style":{"name":"other","confidence":0.972}},"text":"287/150","words":[{"boundingBox":[349,160,455,160,455,184,349,185],"text":"287/150","confidence":0.995}]},{"boundingBox":[24,220,312,217,312,248,24,253],"appearance":{"style":{"name":"other","confidence":0.972}},"text":"Sublegends Baybayin - $50","words":[{"boundingBox":[24,222,111,220,113,251,26,254],"text":"Sublegends","confidence":0.992},{"boundingBox":[117,219,231,218,233,249,119,251],"text":"Baybayin","confidence":0.995},{"boundingBox":[237,218,254,218,255,248,239,249],"text":"-","confidence":0.995},{"boundingBox":[260,218,310,218,311,248,261,248],"text":"$50","confidence":0.979}]},{"boundingBox":[347,218,460,219,460,243,347,243],"appearance":{"style":{"name":"other","confidence":0.972}},"text":"370/150","words":[{"boundingBox":[349,219,454,220,454,243,349,244],"text":"370/150","confidence":0.992}]},{"boundingBox":[24,286,96,287,96,308,24,308],"appearance":{"style":{"name":"other","confidence":0.972}},"text":"Novelties","words":[{"boundingBox":[26,287,96,287,97,309,24,308],"text":"Novelties","confidence":0.992}]},{"boundingBox":[153,278,311,278,311,306,153,306],"appearance":{"style":{"name":"other","confidence":0.972}},"text":"Create - $47","words":[{"boundingBox":[154,279,232,279,232,306,153,306],"text":"Create","confidence":0.993},{"boundingBox":[238,279,253,279,253,306,237,306],"text":"-","confidence":0.995},{"boundingBox":[261,279,309,279,309,307,261,306],"text":"$47","confidence":0.998}]},{"boundingBox":[349,280,460,281,460,304,349,304],"appearance":{"style":{"name":"other","confidence":0.972}},"text":"548/150","words":[{"boundingBox":[351,281,455,282,455,304,350,304],"text":"548/150","confidence":0.993}]},{"boundingBox":[23,349,104,348,104,371,23,372],"appearance":{"style":{"name":"other","confidence":0.972}},"text":"Spacebars","words":[{"boundingBox":[24,350,105,349,105,372,24,372],"text":"Spacebars","confidence":0.995}]},{"boundingBox":[168,339,311,338,311,365,168,366],"appearance":{"style":{"name":"other","confidence":0.972}},"text":"Terra - $33","words":[{"boundingBox":[170,340,232,340,232,367,170,367],"text":"Terra","confidence":0.994},{"boundingBox":[237,340,253,340,253,367,238,367],"text":"-","confidence":0.995},{"boundingBox":[258,340,307,339,308,366,259,367],"text":"$33","confidence":0.998}]},{"boundingBox":[347,340,460,341,460,365,347,365],"appearance":{"style":{"name":"other","confidence":0.972}},"text":"330/100","words":[{"boundingBox":[349,341,455,343,455,365,349,366],"text":"330/100","confidence":0.996}]},{"boundingBox":[26,403,106,403,106,426,26,425],"appearance":{"style":{"name":"other","confidence":0.972}},"text":"RAMA","words":[{"boundingBox":[27,404,99,404,100,427,26,426],"text":"RAMA","confidence":0.991}]},{"boundingBox":[139,408,178,409,178,428,139,428],"appearance":{"style":{"name":"other","confidence":0.915}},"text":"R1 1u","words":[{"boundingBox":[140,408,155,408,154,428,140,427],"text":"R1","confidence":0.685},{"boundingBox":[159,408,178,408,177,428,158,428],"text":"1u","confidence":0.385}]},{"boundingBox":[202,400,312,400,312,427,202,428],"appearance":{"style":{"name":"other","confidence":0.972}},"text":"Eh-$56","words":[{"boundingBox":[203,402,307,400,308,428,203,427],"text":"Eh-$56","confidence":0.902}]},{"boundingBox":[346,401,459,402,459,427,346,426],"appearance":{"style":{"name":"other","confidence":0.972}},"text":"228/100","words":[{"boundingBox":[348,402,456,404,456,426,348,427],"text":"228/100","confidence":0.991}]},{"boundingBox":[71,469,140,469,141,489,71,489],"appearance":{"style":{"name":"other","confidence":0.972}},"text":"R3 Enter","words":[{"boundingBox":[72,470,90,469,90,490,72,490],"text":"R3","confidence":0.995},{"boundingBox":[94,469,140,470,140,490,94,490],"text":"Enter","confidence":0.998}]},{"boundingBox":[154,460,311,459,311,488,154,489],"appearance":{"style":{"name":"other","confidence":0.972}},"text":"Create - $68","words":[{"boundingBox":[155,462,232,461,232,489,154,489],"text":"Create","confidence":0.993},{"boundingBox":[237,461,253,461,254,489,237,489],"text":"-","confidence":0.992},{"boundingBox":[259,461,308,459,310,489,260,489],"text":"$68","confidence":0.981}]},{"boundingBox":[348,463,459,463,459,488,348,488],"appearance":{"style":{"name":"other","confidence":0.972}},"text":"241/100","words":[{"boundingBox":[348,463,455,465,455,488,348,488],"text":"241/100","confidence":0.996}]},{"boundingBox":[25,524,135,523,135,548,25,548],"appearance":{"style":{"name":"other","confidence":0.972}},"text":"Deskmat","words":[{"boundingBox":[26,524,135,524,135,548,26,548],"text":"Deskmat","confidence":0.994}]},{"boundingBox":[203,521,312,522,312,549,203,549],"appearance":{"style":{"name":"other","confidence":0.972}},"text":"Eh- $20","words":[{"boundingBox":[204,523,253,522,253,549,203,549],"text":"Eh-","confidence":0.941},{"boundingBox":[259,522,307,522,307,550,259,549],"text":"$20","confidence":0.991}]},{"boundingBox":[350,524,445,525,445,549,350,548],"appearance":{"style":{"name":"other","confidence":0.972}},"text":"224/20","words":[{"boundingBox":[350,525,440,526,440,548,350,548],"text":"224/20","confidence":0.993}]},{"boundingBox":[195,583,312,582,312,609,195,610],"appearance":{"style":{"name":"other","confidence":0.972}},"text":"Art - $20","words":[{"boundingBox":[196,584,233,584,232,610,195,610],"text":"Art","confidence":0.995},{"boundingBox":[238,584,253,583,252,610,237,610],"text":"-","confidence":0.995},{"boundingBox":[260,583,307,583,307,610,260,610],"text":"$20","confidence":0.993}]},{"boundingBox":[349,584,446,585,446,609,349,609],"appearance":{"style":{"name":"other","confidence":0.972}},"text":"228/20","words":[{"boundingBox":[349,585,438,586,439,609,350,610],"text":"228/20","confidence":0.995}]},{"boundingBox":[57,642,311,642,311,673,57,673],"appearance":{"style":{"name":"other","confidence":0.972}},"text":"Lunar Landing - $20","words":[{"boundingBox":[58,643,125,644,125,674,57,674],"text":"Lunar","confidence":0.997},{"boundingBox":[131,644,232,644,232,674,131,674],"text":"Landing","confidence":0.997},{"boundingBox":[238,644,252,644,252,674,238,674],"text":"-","confidence":0.995},{"boundingBox":[258,644,309,643,310,674,258,674],"text":"$20","confidence":0.991}]},{"boundingBox":[347,645,445,645,445,670,347,670],"appearance":{"style":{"name":"other","confidence":0.972}},"text":"524/20","words":[{"boundingBox":[348,646,440,647,440,670,348,670],"text":"524/20","confidence":0.993}]},{"boundingBox":[1247,638,1369,639,1369,659,1247,658],"appearance":{"style":{"name":"other","confidence":0.972}},"text":"All vendors updated","words":[{"boundingBox":[1249,638,1262,639,1261,658,1247,657],"text":"All","confidence":0.994},{"boundingBox":[1266,639,1313,640,1313,659,1265,658],"text":"vendors","confidence":0.997},{"boundingBox":[1317,640,1369,639,1369,660,1317,659],"text":"updated","confidence":0.997}]},{"boundingBox":[1263,662,1358,663,1358,680,1263,679],"appearance":{"style":{"name":"other","confidence":0.972}},"text":"Extras included","words":[{"boundingBox":[1263,663,1298,663,1297,680,1263,680],"text":"Extras","confidence":0.994},{"boundingBox":[1301,663,1356,663,1355,680,1301,680],"text":"included","confidence":0.996}]},{"boundingBox":[191,706,285,708,284,731,190,729],"appearance":{"style":{"name":"other","confidence":0.972}},"text":"Orders:","words":[{"boundingBox":[192,706,285,708,285,732,191,730],"text":"Orders:","confidence":0.996}]},{"boundingBox":[321,708,341,708,341,731,320,730],"appearance":{"style":{"name":"other","confidence":0.972}},"text":"0","words":[{"boundingBox":[321,708,335,708,334,731,321,730],"text":"0","confidence":0.268}]},{"boundingBox":[662,708,713,708,713,730,662,730],"appearance":{"style":{"name":"other","confidence":0.972}},"text":"500","words":[{"boundingBox":[662,708,707,708,707,730,662,730],"text":"500","confidence":0.998}]},{"boundingBox":[1012,708,1076,709,1077,730,1012,730],"appearance":{"style":{"name":"other","confidence":0.972}},"text":"1000","words":[{"boundingBox":[1013,708,1070,708,1070,730,1013,729],"text":"1000","confidence":0.989}]},{"boundingBox":[1367,708,1431,708,1431,730,1367,730],"appearance":{"style":{"name":"other","confidence":0.972}},"text":"1500","words":[{"boundingBox":[1368,708,1426,708,1426,730,1368,730],"text":"1500","confidence":0.989}]}]}]